get_wrapped/__init__.py
get_wrapped/_client.py
get_wrapped/summarize.py
get_wrapped/wrapped.py
get_wrapped-0.1.3.dist-info/WHEEL
get_wrapped-0.1.3.dist-info/METADATA
get_wrapped-0.1.3.dist-info/RECORD
