Metadata-Version: 2.3
Name: get-wrapped
Version: 0.1.3
Summary: Create your own Wrapped-style summary from any dataset
Author: Kushagra Kumar
License: MIT
Requires-Dist: requests>=2.32.2
Requires-Dist: pandas>=2.2.3
Requires-Dist: python-dotenv>=1.0.1
Requires-Python: >=3.13
